{
    "Number":  261,
    "Message":  "- Configuration files can now be loaded/saved from any folder.\r\n- Resuming from sleep should no longer trigger a ask for save.\r\n- Graph point should now update properly on cancel",
    "Checksums":  {
                      "FanControl_4_8":  "893288F9E2E4657731C7981EB94BF166",
                      "FanControl_10_0":  "B99A6A9D1C36AD2D60FE76098C2C3E02",
                      "FanControl_4_8_Installer":  "9D78BA022E27B27B3AB8E372C5242228",
                      "FanControl_10_0_Installer":  "CED733AAB0269E8543BA0F8F27010C8D",
                      "Updater":  "8445CA16D4EC4D0791F71C025B56FF0C"
                  }
}
